ewoksnotify/__init__.py
ewoksnotify/gui/__init__.py
ewoksnotify/gui/actions.py
ewoksnotify/gui/email.py
ewoksnotify/gui/icat.py
ewoksnotify/gui/tone.py
ewoksnotify/gui/utils/__init__.py
ewoksnotify/gui/utils/buttons.py
ewoksnotify/resources/__init__.py
ewoksnotify/resources/gui/icons/compose.png
ewoksnotify/resources/gui/icons/compose.svg
ewoksnotify/resources/gui/icons/locked.png
ewoksnotify/resources/gui/icons/locked.svg
ewoksnotify/resources/gui/icons/parameters.png
ewoksnotify/resources/gui/icons/parameters.svg
ewoksnotify/resources/gui/icons/unlocked.png
ewoksnotify/resources/gui/icons/unlocked.svg
ewoksnotify/tasks/__init__.py
ewoksnotify/tasks/email.py
ewoksnotify/tasks/get_from_data.py
ewoksnotify/tasks/icat.py
ewoksnotify/tasks/tone.py
ewoksnotify/tasks/waiter.py
ewoksnotify/tests/__init__.py
ewoksnotify/tests/conftest.py
ewoksnotify/tests/gui/__init__.py
ewoksnotify/tests/gui/test_email_gui.py
ewoksnotify/tests/gui/test_tone_gui.py
ewoksnotify/tests/tasks/__init__.py
ewoksnotify/tests/tasks/test_get_from_data.py
ewoksnotify/tests/tasks/test_icat.py
ewoksnotify/tests/tasks/test_tone.py
ewoksnotify/tests/tasks/test_waiter.py
ewoksnotify/utils/__init__.py
ewoksnotify/utils/beamlines.py
orangecontrib/ewoksnotify/ToneNotifierOW.py
orangecontrib/ewoksnotify/WaiterOW.py
orangecontrib/ewoksnotify/__init__.py
orangecontrib/ewoksnotify/icons/__init__.py
orangecontrib/ewoksnotify/icons/category.svg
orangecontrib/ewoksnotify/icons/email.png
orangecontrib/ewoksnotify/icons/email.svg
orangecontrib/ewoksnotify/icons/notification.png
orangecontrib/ewoksnotify/icons/notification.svg
orangecontrib/ewoksnotify/icons/publish_processed_data.png
orangecontrib/ewoksnotify/icons/publish_processed_data.svg
orangecontrib/ewoksnotify/icons/waiter.png
ewoksnotify-0.1.3.dist-info/LICENSE.md
ewoksnotify-0.1.3.dist-info/METADATA
ewoksnotify-0.1.3.dist-info/WHEEL
ewoksnotify-0.1.3.dist-info/entry_points.txt
ewoksnotify-0.1.3.dist-info/top_level.txt
ewoksnotify-0.1.3.dist-info/RECORD
